redshift_connector/__init__.py
redshift_connector/config.py
redshift_connector/core.py
redshift_connector/credentials_holder.py
redshift_connector/cursor.py
redshift_connector/error.py
redshift_connector/iam_helper.py
redshift_connector/idp_auth_helper.py
redshift_connector/interval.py
redshift_connector/metadataAPIHelper.py
redshift_connector/metadataAPIPostProcessing.py
redshift_connector/metadataServerAPIHelper.py
redshift_connector/native_plugin_helper.py
redshift_connector/objects.py
redshift_connector/pg_types.py
redshift_connector/redshift_property.py
redshift_connector/version.py
redshift_connector/auth/__init__.py
redshift_connector/auth/aws_credentials_provider.py
redshift_connector/files/redshift-ca-bundle.crt
redshift_connector/plugin/__init__.py
redshift_connector/plugin/adfs_credentials_provider.py
redshift_connector/plugin/azure_credentials_provider.py
redshift_connector/plugin/browser_azure_credentials_provider.py
redshift_connector/plugin/browser_azure_oauth2_credentials_provider.py
redshift_connector/plugin/browser_idc_auth_plugin.py
redshift_connector/plugin/browser_saml_credentials_provider.py
redshift_connector/plugin/common_credentials_provider.py
redshift_connector/plugin/credential_provider_constants.py
redshift_connector/plugin/i_native_plugin.py
redshift_connector/plugin/i_plugin.py
redshift_connector/plugin/idp_credentials_provider.py
redshift_connector/plugin/idp_token_auth_plugin.py
redshift_connector/plugin/jwt_credentials_provider.py
redshift_connector/plugin/native_token_holder.py
redshift_connector/plugin/okta_credentials_provider.py
redshift_connector/plugin/ping_credentials_provider.py
redshift_connector/plugin/saml_credentials_provider.py
redshift_connector/utils/__init__.py
redshift_connector/utils/array_util.py
redshift_connector/utils/driver_info.py
redshift_connector/utils/extensible_digest.py
redshift_connector/utils/logging_utils.py
redshift_connector/utils/oids.py
redshift_connector/utils/sql_types.py
redshift_connector-2.1.9.dist-info/LICENSE
redshift_connector-2.1.9.dist-info/METADATA
redshift_connector-2.1.9.dist-info/NOTICE
redshift_connector-2.1.9.dist-info/WHEEL
redshift_connector-2.1.9.dist-info/top_level.txt
redshift_connector-2.1.9.dist-info/RECORD
