Metadata-Version: 2.1
Name: redshift-connector
Version: 2.1.9
Summary: Redshift interface library
Home-page: https://github.com/aws/amazon-redshift-python-driver
Author: Amazon Web Services
Author-email: redshift-drivers@amazon.com
License: Apache License 2.0
Keywords: redshift dbapi
Platform: UNKNOWN
Classifier: Development Status :: 5 - Production/Stable
Classifier: Intended Audience :: Developers
Classifier: License :: OSI Approved :: BSD License
Classifier: Programming Language :: Python
Classifier: Programming Language :: Python :: 3
Classifier: Programming Language :: Python :: 3.6
Classifier: Programming Language :: Python :: 3.7
Classifier: Programming Language :: Python :: 3.8
Classifier: Programming Language :: Python :: 3.9
Classifier: Programming Language :: Python :: 3.10
Classifier: Programming Language :: Python :: 3.11
Classifier: Programming Language :: Python :: Implementation
Classifier: Programming Language :: Python :: Implementation :: CPython
Classifier: Programming Language :: Python :: Implementation :: Jython
Classifier: Programming Language :: Python :: Implementation :: PyPy
Classifier: Operating System :: OS Independent
Classifier: Topic :: Database :: Front-Ends
Classifier: Topic :: Software Development :: Libraries :: Python Modules
Requires-Python: >=3.6
License-File: LICENSE
License-File: NOTICE
Requires-Dist: scramp (<1.5.0,>=1.2.0)
Requires-Dist: pytz (>=2020.1)
Requires-Dist: beautifulsoup4 (<5.0.0,>=4.7.0)
Requires-Dist: boto3 (<2.0.0,>=1.9.201)
Requires-Dist: requests (<3.0.0,>=2.23.0)
Requires-Dist: lxml (<6.0.0,>=4.6.5)
Requires-Dist: botocore (<2.0.0,>=1.12.201)
Requires-Dist: packaging
Requires-Dist: setuptools
Provides-Extra: full
Requires-Dist: numpy ; extra == 'full'
Requires-Dist: pandas ; extra == 'full'
